{
  "vertices": {
    "0": {
      "position": {
        "x": 1.5,
        "y": -10
      },
      "associated_graph": {
        "vertices": {
          "0": {
            "position": {
              "x": -0.28896766313551187,
              "y": 0.3925616729525966
            }
          },
          "1": {
            "position": {
              "x": -0.3040085690267775,
              "y": -0.21717596157184166
            }
          },
          "2": {
            "position": {
              "x": 0.29769546506947575,
              "y": 0.22575053031074893
            }
          },
          "3": {
            "position": {
              "x": -0.7047192329071865,
              "y": -0.8280001403499749
            }
          },
          "4": {
            "position": {
              "x": 1.0,
              "y": 0.4268638986584708
            }
          }
        },
        "edges": [
          [
            0,
            1
          ],
          [
            0,
            2
          ],
          [
            1,
            2
          ],
          [
            1,
            3
          ],
          [
            2,
            4
          ]
        ]
      }
    },
    "0-0": {
      "position": {
        "x": 0.5,
        "y": -20
      },
      "associated_graph": {
        "vertices": {
          "0": {
            "position": {
              "x": 0.1766555152960303,
              "y": -0.3256200466500152
            }
          },
          "1": {
            "position": {
              "x": 0.3693356447632667,
              "y": -0.29827106301751016
            }
          },
          "2": {
            "position": {
              "x": 0.23973528441050587,
              "y": -0.10281583549994713
            }
          },
          "3": {
            "position": {
              "x": -1.0,
              "y": 0.5751876497640837
            }
          },
          "4": {
            "position": {
              "x": 0.21427355553019725,
              "y": 0.1515192954033888
            }
          }
        },
        "edges": [
          [
            0,
            1
          ],
          [
            0,
            2
          ],
          [
            1,
            2
          ],
          [
            2,
            4
          ]
        ]
      }
    },
    "0-1": {
      "position": {
        "x": 1.5,
        "y": -20
      },
      "associated_graph": {
        "vertices": {
          "0": {
            "position": {
              "x": -0.0008400431951464323,
              "y": 0.0031622286627336826
            }
          },
          "1": {
            "position": {
              "x": 0.5326498150769889,
              "y": -0.11803265437825125
            }
          },
          "2": {
            "position": {
              "x": -0.5316892870248155,
              "y": 0.12018354249354384
            }
          },
          "3": {
            "position": {
              "x": 0.9998795151429729,
              "y": -0.2262947497920915
            }
          },
          "4": {
            "position": {
              "x": -1.0,
              "y": 0.22098163301406493
            }
          }
        },
        "edges": [
          [
            0,
            1
          ],
          [
            0,
            2
          ],
          [
            1,
            3
          ],
          [
            2,
            4
          ]
        ]
      }
    },
    "0-2": {
      "position": {
        "x": 2.5,
        "y": -20
      },
      "associated_graph": {
        "vertices": {
          "0": {
            "position": {
              "x": -0.9203776510642261,
              "y": -0.2526218582560578
            }
          },
          "1": {
            "position": {
              "x": 0.3442602431326702,
              "y": 0.43447051177278034
            }
          },
          "2": {
            "position": {
              "x": -0.18016530890110763,
              "y": -0.22742050999403612
            }
          },
          "3": {
            "position": {
              "x": 0.7931228551814397,
              "y": 1.0
            }
          },
          "4": {
            "position": {
              "x": -0.036840138348776065,
              "y": -0.9544281435226863
            }
          }
        },
        "edges": [
          [
            0,
            2
          ],
          [
            1,
            2
          ],
          [
            1,
            3
          ],
          [
            2,
            4
          ]
        ]
      }
    },
    "0-0-0": {
      "position": {
        "x": 0.0,
        "y": -30
      },
      "associated_graph": {
        "vertices": {
          "0": {
            "position": {
              "x": 0.4720493847593636,
              "y": -0.41780652392425444
            }
          },
          "1": {
            "position": {
              "x": 0.32431709629954114,
              "y": -0.4007528520808292
            }
          },
          "2": {
            "position": {
              "x": 0.4091535509883045,
              "y": -0.2819884246208214
            }
          },
          "3": {
            "position": {
              "x": -1.0,
              "y": 0.13528275056865954
            }
          },
          "4": {
            "position": {
              "x": -0.20552003204720928,
              "y": 0.9652650500572455
            }
          }
        },
        "edges": [
          [
            0,
            1
          ],
          [
            0,
            2
          ],
          [
            1,
            2
          ]
        ]
      }
    },
    "0-0-1": {
      "position": {
        "x": 1.0,
        "y": -30
      },
      "associated_graph": {
        "vertices": {
          "0": {
            "position": {
              "x": -0.04480870283328689,
              "y": 0.5991622119846903
            }
          },
          "1": {
            "position": {
              "x": 0.08168653982106736,
              "y": 0.36257111656197893
            }
          },
          "2": {
            "position": {
              "x": 0.24711919091976603,
              "y": 0.11895414797352742
            }
          },
          "3": {
            "position": {
              "x": -0.7070521741409118,
              "y": -1.0
            }
          },
          "4": {
            "position": {
              "x": 0.42305514623336554,
              "y": -0.08068747652019684
            }
          }
        },
        "edges": [
          [
            0,
            1
          ],
          [
            1,
            2
          ],
          [
            2,
            4
          ]
        ]
      }
    },
    "0-0-2": {
      "position": {
        "x": 2.0,
        "y": -30
      },
      "associated_graph": {
        "vertices": {
          "0": {
            "position": {
              "x": -0.028349955057581283,
              "y": -0.20101697428167514
            }
          },
          "1": {
            "position": {
              "x": 0.42946497817131485,
              "y": -0.30179426118664
            }
          },
          "2": {
            "position": {
              "x": 0.24160006717791735,
              "y": -0.07073360276094565
            }
          },
          "3": {
            "position": {
              "x": -0.9999999999999999,
              "y": 0.35528443805077015
            }
          },
          "4": {
            "position": {
              "x": 0.35728490970834864,
              "y": 0.21826040017849066
            }
          }
        },
        "edges": [
          [
            0,
            2
          ],
          [
            1,
            2
          ],
          [
            2,
            4
          ]
        ]
      }
    },
    "0-1-3": {
      "position": {
        "x": 3.0,
        "y": -30
      },
      "associated_graph": {
        "vertices": {
          "0": {
            "position": {
              "x": 0.5516677915969953,
              "y": 0.6210445250516379
            }
          },
          "1": {
            "position": {
              "x": -0.9853231986172584,
              "y": -0.48199388533237797
            }
          },
          "2": {
            "position": {
              "x": 0.6167315883325418,
              "y": 0.3682309906334199
            }
          },
          "3": {
            "position": {
              "x": -1.0,
              "y": -0.7071061837848062
            }
          },
          "4": {
            "position": {
              "x": 0.8169238186877213,
              "y": 0.19982455343212602
            }
          }
        },
        "edges": [
          [
            0,
            2
          ],
          [
            1,
            3
          ],
          [
            2,
            4
          ]
        ]
      }
    },
    "0-0-0-0": {
      "position": {
        "x": 1.0,
        "y": -40
      },
      "associated_graph": {
        "vertices": {
          "0": {
            "position": {
              "x": 0.5810886001717324,
              "y": 0.180257386323474
            }
          },
          "1": {
            "position": {
              "x": 0.2486723227727408,
              "y": 0.3924822960606159
            }
          },
          "2": {
            "position": {
              "x": 0.4096653325564664,
              "y": 0.27915095198164414
            }
          },
          "3": {
            "position": {
              "x": -0.9424368227079397,
              "y": 0.14810936563426597
            }
          },
          "4": {
            "position": {
              "x": -0.2969894327929999,
              "y": -1.0
            }
          }
        },
        "edges": [
          [
            0,
            2
          ],
          [
            1,
            2
          ]
        ]
      }
    },
    "0-0-1-1": {
      "position": {
        "x": 2.0,
        "y": -40
      },
      "associated_graph": {
        "vertices": {
          "0": {
            "position": {
              "x": -0.780768833959472,
              "y": -0.6520013421465949
            }
          },
          "1": {
            "position": {
              "x": -0.5880060389204458,
              "y": -0.4688092332544152
            }
          },
          "2": {
            "position": {
              "x": 0.9496478721619811,
              "y": -0.05567454032088561
            }
          },
          "3": {
            "position": {
              "x": -0.5808729992820634,
              "y": 0.9922555341532845
            }
          },
          "4": {
            "position": {
              "x": 1.0,
              "y": 0.18422958156861122
            }
          }
        },
        "edges": [
          [
            0,
            1
          ],
          [
            2,
            4
          ]
        ]
      }
    },
    "0-0-0-0-0": {
      "position": {
        "x": 1.5,
        "y": -50
      },
      "associated_graph": {
        "vertices": {
          "0": {
            "position": {
              "x": -1.0,
              "y": -0.9884453195698832
            }
          },
          "1": {
            "position": {
              "x": 0.5765202849296727,
              "y": 0.6091816199766855
            }
          },
          "2": {
            "position": {
              "x": 0.4415031148371697,
              "y": 0.4372223336302084
            }
          },
          "3": {
            "position": {
              "x": 0.9572514621244408,
              "y": -0.7523024706926069
            }
          },
          "4": {
            "position": {
              "x": -0.975274861891283,
              "y": 0.6943438366555958
            }
          }
        },
        "edges": [
          [
            1,
            2
          ]
        ]
      }
    },
    "0-0-0-0-0-0": {
      "position": {
        "x": 1.5,
        "y": -60
      },
      "associated_graph": {
        "vertices": {
          "0": {
            "position": {
              "x": 0.7037459486044496,
              "y": 0.5474331483396778
            }
          },
          "1": {
            "position": {
              "x": -1.0,
              "y": -0.17539648980753458
            }
          },
          "2": {
            "position": {
              "x": 0.8068493220472612,
              "y": -0.5346163923324613
            }
          },
          "3": {
            "position": {
              "x": -0.281776135546708,
              "y": 0.9599873144660677
            }
          },
          "4": {
            "position": {
              "x": -0.2288191351050029,
              "y": -0.7974075806657497
            }
          }
        },
        "edges": []
      }
    }
  },
  "edges": [
    [
      "0",
      "0-0"
    ],
    [
      "0",
      "0-1"
    ],
    [
      "0",
      "0-2"
    ],
    [
      "0-0",
      "0-0-0"
    ],
    [
      "0-0",
      "0-0-1"
    ],
    [
      "0-0",
      "0-0-2"
    ],
    [
      "0-1",
      "0-0-1"
    ],
    [
      "0-1",
      "0-1-3"
    ],
    [
      "0-2",
      "0-0-2"
    ],
    [
      "0-2",
      "0-1-3"
    ],
    [
      "0-2",
      "0-0-1"
    ],
    [
      "0-0-0",
      "0-0-0-0"
    ],
    [
      "0-0-1",
      "0-0-1-1"
    ],
    [
      "0-0-1",
      "0-0-0-0"
    ],
    [
      "0-0-2",
      "0-0-0-0"
    ],
    [
      "0-1-3",
      "0-0-0-0"
    ],
    [
      "0-1-3",
      "0-0-1-1"
    ],
    [
      "0-0-0-0",
      "0-0-0-0-0"
    ],
    [
      "0-0-1-1",
      "0-0-0-0-0"
    ],
    [
      "0-0-0-0-0",
      "0-0-0-0-0-0"
    ]
  ],
  "ramsey_set": []
}